LICENSE
saleor_flat_tax_plugin/__init__.py
saleor_flat_tax_plugin/plugin.py
saleor_flat_tax_plugin-0.5.1.dist-info/entry_points.txt
saleor_flat_tax_plugin-0.5.1.dist-info/LICENSE
saleor_flat_tax_plugin-0.5.1.dist-info/WHEEL
saleor_flat_tax_plugin-0.5.1.dist-info/METADATA
saleor_flat_tax_plugin-0.5.1.dist-info/RECORD
