Metadata-Version: 2.1
Name: saleor-flat-tax-plugin
Version: 0.5.1
Summary: Saleor Flat Tax Plugin
Home-page: https://github.com/carlosa54/saleor-flat-tax-plugin
License: MIT
Keywords: saleor,plugins
Author: Carlos Ramírez
Author-email: carlosarg54@gmail.com
Requires-Python: >=3.9,<3.10
Classifier: License :: OSI Approved :: MIT License
Classifier: Programming Language :: Python :: 3
Classifier: Programming Language :: Python :: 3.9
Project-URL: Repository, https://github.com/carlosa54/saleor-flat-tax-plugin
